README.md
package_info.json
setup.py
th2_grpc_read_db/__init__.py
th2_grpc_read_db/py.typed
th2_grpc_read_db/read_db.proto
th2_grpc_read_db/read_db_pb2.py
th2_grpc_read_db/read_db_pb2.pyi
th2_grpc_read_db/read_db_pb2_grpc.py
th2_grpc_read_db.egg-info/PKG-INFO
th2_grpc_read_db.egg-info/SOURCES.txt
th2_grpc_read_db.egg-info/dependency_links.txt
th2_grpc_read_db.egg-info/requires.txt
th2_grpc_read_db.egg-info/top_level.txt