Metadata-Version: 2.4
Name: th2_grpc_read_db
Version: 0.0.12rc1
Summary: th2_grpc_read_db
Home-page: https://github.com/th2-net/th2-read-db
Author: TH2-devs
Author-email: th2-devs@exactprosystems.com
License: Apache License 2.0
Requires-Python: >=3.7
Requires-Dist: grpcio-tools==1.56.0
Requires-Dist: th2-grpc-common==4.5.0rc1
Requires-Dist: mypy-protobuf==3.4
Dynamic: author
Dynamic: author-email
Dynamic: description
Dynamic: description-content-type
Dynamic: home-page
Dynamic: license
Dynamic: requires-dist
Dynamic: requires-python
Dynamic: summary
